mailpapa/__init__.py
mailpapa/__version__.py
mailpapa/api.py
mailpapa/cli.py
mailpapa/compatible.py
mailpapa/models.py
mailpapa/parse.py
mailpapa/structures.py
mailpapa/utils.py
mailpapa-0.1.5.dist-info/LICENSE.txt
mailpapa-0.1.5.dist-info/METADATA
mailpapa-0.1.5.dist-info/RECORD
mailpapa-0.1.5.dist-info/WHEEL
mailpapa-0.1.5.dist-info/entry_points.txt
mailpapa-0.1.5.dist-info/top_level.txt
tests/__init__.py
tests/stub.py
